pet_lang/__init__.py
pet_lang/__main__.py
pet_lang/pet_lang.py
tests/__init__.py
tests/test_pet_lang.py
pet_lang-1.0.0.dist-info/LICENSE
pet_lang-1.0.0.dist-info/METADATA
pet_lang-1.0.0.dist-info/WHEEL
pet_lang-1.0.0.dist-info/top_level.txt
pet_lang-1.0.0.dist-info/RECORD
